napari_dzi_zarr/__init__.py
napari_dzi_zarr/_version.py
napari_dzi_zarr/dzi_zarr.py
napari_dzi_zarr/store.py
napari_dzi_zarr/_tests/__init__.py
napari_dzi_zarr/_tests/test_dzi_zarr.py
napari_dzi_zarr-0.1.2.dist-info/LICENSE
napari_dzi_zarr-0.1.2.dist-info/METADATA
napari_dzi_zarr-0.1.2.dist-info/WHEEL
napari_dzi_zarr-0.1.2.dist-info/entry_points.txt
napari_dzi_zarr-0.1.2.dist-info/top_level.txt
napari_dzi_zarr-0.1.2.dist-info/RECORD
