Metadata-Version: 2.1
Name: napari-dzi-zarr
Version: 0.1.2
Summary: An experimental plugin for viewing Deep Zoom Images (DZI) with napari and zarr.
Home-page: https://github.com/manzt/napari-dzi-zarr
Author: Trevor Manz
Author-email: trevor.j.manz@gmail.com
License: BSD-3
Platform: UNKNOWN
Classifier: Development Status :: 4 - Beta
Classifier: Intended Audience :: Developers
Classifier: Topic :: Software Development :: Testing
Classifier: Programming Language :: Python
Classifier: Programming Language :: Python :: 3
Classifier: Programming Language :: Python :: 3.6
Classifier: Programming Language :: Python :: 3.7
Classifier: Programming Language :: Python :: 3.8
Classifier: Programming Language :: Python :: Implementation :: CPython
Classifier: Programming Language :: Python :: Implementation :: PyPy
Classifier: Operating System :: OS Independent
Classifier: License :: OSI Approved :: BSD License
Classifier: Framework :: napari
Requires-Python: >=3.6
Requires-Dist: napari-plugin-engine (>=0.1.4)
Requires-Dist: numpy (>=0.1.19)
Requires-Dist: zarr (>=0.2.4)
Requires-Dist: dask[array] (>=2.23.0)
Requires-Dist: fsspec (>=0.8.0)
Requires-Dist: requests (>=2.24.0)
Requires-Dist: aiohttp (>=3.6.2)
Requires-Dist: imageio (>=2.9.0)
